py_service_object/__init__.py
py_service_object/service_object.py
py_service_object-0.1.1.dist-info/METADATA
py_service_object-0.1.1.dist-info/WHEEL
py_service_object-0.1.1.dist-info/licenses/LICENSE
py_service_object-0.1.1.dist-info/RECORD
