Metadata-Version: 2.3
Name: py-service-object
Version: 0.1.1
Summary: A Python implementation of the Service Object pattern, inspired by Ruby's SimpleCommand gem
Project-URL: Homepage, https://github.com/vitrpereira/py-service-object
Author-email: Vitor Pereira <pvitorpereira@gmail.com>
License: MIT License
Keywords: business-logic,design-pattern,service-object
Classifier: License :: OSI Approved :: MIT License
Classifier: Operating System :: OS Independent
Classifier: Programming Language :: Python :: 3
Requires-Python: >=3.8
